{"cameraMode":{"drawMode":0,"name":"Shaded","section":"Shading Mode"},"sceneLighting":true,"audioPlay":false,"sceneViewState":{"m_AlwaysRefresh":false,"showFog":true,"showSkybox":true,"showFlares":true,"showImageEffects":true,"showParticleSystems":true,"showVisualEffectGraphs":true,"m_FxEnabled":true},"in2DMode":false,"pivot":{"x":-5.631152153015137,"y":2.5718483924865724,"z":-4.65287971496582},"rotation":{"x":0.008898759260773659,"y":0.990237295627594,"z":-0.07530409097671509,"w":0.11698897182941437},"size":14.707098007202149,"orthographic":false}